anythumbnailer-0.1.dist-info/METADATA
anythumbnailer-0.1.dist-info/top_level.txt
anythumbnailer-0.1.dist-info/entry_points.txt
anythumbnailer-0.1.dist-info/DESCRIPTION.rst
anythumbnailer-0.1.dist-info/metadata.json
anythumbnailer-0.1.dist-info/WHEEL
anythumbnailer-0.1.dist-info/RECORD
anythumbnailer/thumbnail_.py
anythumbnailer/__init__.py
anythumbnailer/sh_utils.py
anythumbnailer/cli.py
