Metadata-Version: 2.0
Name: anythumbnailer
Version: 0.1
Summary: Generic Thumbnailer library
Home-page: https://github.com/FelixSchwarz/anythumbnailer
Author: Felix Schwarz
Author-email: info@schwarz.eu
License: MIT
Platform: UNKNOWN
